{
  "17_beta": {
    "type": "catalogRender",
    "schema": 1,
    "eval": {
      "version": "17_beta",
      "pname": "openvpn3",
      "name": "openvpn3-17_beta",
      "system": "x86_64-linux",
      "outputs": {
        "out": "/nix/store/pl50qwhx5b3xgqa4byzxaga11m0jl70k-openvpn3-17_beta"
      },
      "meta": {
        "outputsToInstall": [
          "out"
        ],
        "description": "OpenVPN 3 Linux client",
        "position": "/nix/store/gk9ag5wlkhwi4qbn56fx77g3v41n2a5g-source/pkgs/tools/networking/openvpn3/default.nix:119",
        "unfree": false
      }
    },
    "element": {
      "attrPath": [
        "legacyPackages",
        "x86_64-linux",
        "openvpn3"
      ],
      "originalUrl": "flake:nixpkgs",
      "outputs": null,
      "storePaths": [
        "/nix/store/pl50qwhx5b3xgqa4byzxaga11m0jl70k-openvpn3-17_beta"
      ],
      "url": "github:flox/nixpkgs/12363fb6d89859a37cd7e27f85288599f13e49d9"
    },
    "source": {
      "locked": {
        "revCount": 397203,
        "lastModified": 1659487974
      }
    }
  },
  "18_beta": {
    "type": "catalogRender",
    "schema": 1,
    "eval": {
      "version": "18_beta",
      "pname": "openvpn3",
      "name": "openvpn3-18_beta",
      "system": "x86_64-linux",
      "outputs": {
        "out": "/nix/store/3dpl4wsxrsdq5sbkd7ksyn6xc714c3wz-openvpn3-18_beta"
      },
      "meta": {
        "outputsToInstall": [
          "out"
        ],
        "description": "OpenVPN 3 Linux client",
        "position": "/nix/store/9m8drnpifyl5qsx93g6ll2xw6wkps03z-source/pkgs/tools/networking/openvpn3/default.nix:109",
        "unfree": false
      }
    },
    "element": {
      "attrPath": [
        "legacyPackages",
        "x86_64-linux",
        "openvpn3"
      ],
      "originalUrl": "flake:nixpkgs",
      "outputs": null,
      "storePaths": [
        "/nix/store/3dpl4wsxrsdq5sbkd7ksyn6xc714c3wz-openvpn3-18_beta"
      ],
      "url": "github:flox/nixpkgs/f994293d1eb8812f032e8919e10a594567cf6ef7"
    },
    "source": {
      "locked": {
        "revCount": 420742,
        "lastModified": 1666703756
      }
    }
  }
}
