{
  "1.2.56": {
    "type": "catalogRender",
    "schema": 1,
    "eval": {
      "version": "1.2.56",
      "pname": "SDL_compat",
      "name": "SDL_compat-1.2.56",
      "system": "x86_64-linux",
      "outputs": {
        "out": "/nix/store/izqkanyxy0sfxw5i8ldarmwa9iwsh6z9-SDL_compat-1.2.56"
      },
      "meta": {
        "outputsToInstall": [
          "out"
        ],
        "description": "A cross-platform multimedia library - build SDL 1.2 applications against 2.0",
        "position": "/nix/store/lbf0kbc67zpm6xw6lia2fj1qskikaffz-source/pkgs/development/libraries/SDL_compat/default.nix:53",
        "unfree": false
      }
    },
    "element": {
      "attrPath": [
        "legacyPackages",
        "x86_64-linux",
        "SDL_compat"
      ],
      "originalUrl": "flake:nixpkgs",
      "outputs": null,
      "storePaths": [
        "/nix/store/izqkanyxy0sfxw5i8ldarmwa9iwsh6z9-SDL_compat-1.2.56"
      ],
      "url": "github:flox/nixpkgs/d6490a0bd9dfb298fcd8382d3363b86870dc7340"
    },
    "source": {
      "locked": {
        "revCount": 410349,
        "lastModified": 1663761423
      }
    }
  },
  "1.2.52": {
    "type": "catalogRender",
    "schema": 1,
    "eval": {
      "version": "1.2.52",
      "pname": "SDL_compat",
      "name": "SDL_compat-1.2.52",
      "system": "x86_64-linux",
      "outputs": {
        "out": "/nix/store/5pznrwcvj06mh0zz0bcgy9lh6wbykxpi-SDL_compat-1.2.52"
      },
      "meta": {
        "outputsToInstall": [
          "out"
        ],
        "description": "A cross-platform multimedia library - build SDL 1.2 applications against 2.0",
        "position": "/nix/store/5g0bnn21bqpd241da9yyivjkcfy0ra1w-source/pkgs/development/libraries/SDL_compat/default.nix:47",
        "unfree": false
      }
    },
    "element": {
      "attrPath": [
        "legacyPackages",
        "x86_64-linux",
        "SDL_compat"
      ],
      "originalUrl": "flake:nixpkgs",
      "outputs": null,
      "storePaths": [
        "/nix/store/5pznrwcvj06mh0zz0bcgy9lh6wbykxpi-SDL_compat-1.2.52"
      ],
      "url": "github:flox/nixpkgs/e0169d7a9d324afebf5679551407756c77af8930"
    },
    "source": {
      "locked": {
        "revCount": 384129,
        "lastModified": 1654682581
      }
    }
  }
}
