{
  "0.244": {
    "type": "catalogRender",
    "schema": 1,
    "eval": {
      "version": "0.244",
      "pname": "docbook2odf",
      "name": "docbook2odf-0.244",
      "system": "x86_64-linux",
      "outputs": {
        "out": "/nix/store/lhda4rkav10qsnilfd7vnigq701ca23w-docbook2odf-0.244"
      },
      "meta": {
        "outputsToInstall": [
          "out"
        ],
        "description": "Convert DocBook to OpenDocument Format (ODF)",
        "position": "/nix/store/a3i6cnnswvdg4k38jmibnjms65rjvyi7-source/pkgs/tools/typesetting/docbook2odf/default.nix:36",
        "unfree": false
      }
    },
    "element": {
      "attrPath": [
        "legacyPackages",
        "x86_64-linux",
        "docbook2odf"
      ],
      "originalUrl": "flake:nixpkgs",
      "outputs": null,
      "storePaths": [
        "/nix/store/lhda4rkav10qsnilfd7vnigq701ca23w-docbook2odf-0.244"
      ],
      "url": "github:flox/nixpkgs/dfd82985c273aac6eced03625f454b334daae2e8"
    },
    "source": {
      "locked": {
        "revCount": 379159,
        "lastModified": 1653060744
      }
    }
  }
}
