{
  "0.1.0-alpha.9": {
    "type": "catalogRender",
    "schema": 1,
    "eval": {
      "version": "0.1.0-alpha.9",
      "pname": "flintlock",
      "name": "flintlock-0.1.0-alpha.9",
      "system": "x86_64-linux",
      "outputs": {
        "out": "/nix/store/lirlw9fkl7f3pw5h85c8s49sm18n7877-flintlock-0.1.0-alpha.9"
      },
      "meta": {
        "outputsToInstall": [
          "out"
        ],
        "description": "Create and manage the lifecycle of MicroVMs backed by containerd",
        "position": "/nix/store/a3i6cnnswvdg4k38jmibnjms65rjvyi7-source/pkgs/applications/virtualization/flintlock/default.nix:43",
        "unfree": false
      }
    },
    "element": {
      "attrPath": [
        "legacyPackages",
        "x86_64-linux",
        "flintlock"
      ],
      "originalUrl": "flake:nixpkgs",
      "outputs": null,
      "storePaths": [
        "/nix/store/lirlw9fkl7f3pw5h85c8s49sm18n7877-flintlock-0.1.0-alpha.9"
      ],
      "url": "github:flox/nixpkgs/dfd82985c273aac6eced03625f454b334daae2e8"
    },
    "source": {
      "locked": {
        "revCount": 379159,
        "lastModified": 1653060744
      }
    }
  }
}
