{
  "0.7.3": {
    "type": "catalogRender",
    "schema": 1,
    "eval": {
      "version": "0.7.3",
      "pname": "haruna",
      "name": "haruna-0.7.3",
      "system": "x86_64-linux",
      "outputs": {
        "out": "/nix/store/z05sm0l4kyg2670i3y47qvqb8d21m4yj-haruna-0.7.3"
      },
      "meta": {
        "outputsToInstall": [
          "out"
        ],
        "description": "Open source video player built with Qt/QML and libmpv",
        "position": "/nix/store/a3i6cnnswvdg4k38jmibnjms65rjvyi7-source/pkgs/applications/video/haruna/default.nix:70",
        "unfree": false
      }
    },
    "element": {
      "attrPath": "legacyPackages.x86_64-linux.stable.haruna",
      "originalUrl": "flake:floxpkgs",
      "outputs": null,
      "storePaths": [
        "/nix/store/z05sm0l4kyg2670i3y47qvqb8d21m4yj-haruna-0.7.3"
      ],
      "url": "github:flox/floxpkgs/dfd82985c273aac6eced03625f454b334daae2e8"
    },
    "source": {
      "locked": {
        "revCount": 379159,
        "lastModified": 1653060744
      }
    }
  }
}
