{
  "2.0.3": {
    "type": "catalogRender",
    "schema": 1,
    "eval": {
      "version": "2.0.3",
      "pname": "libmng",
      "name": "libmng-2.0.3",
      "system": "aarch64-linux",
      "outputs": {
        "dev": "/nix/store/k8dyagr9pgif52sx93wrkzick2392n1v-libmng-2.0.3-dev",
        "devdoc": "/nix/store/2nfppmynckcgdqqib7150hdmfdpyw05i-libmng-2.0.3-devdoc",
        "out": "/nix/store/scyqns8a6jij8bss704afsxr4vsgiyvx-libmng-2.0.3"
      },
      "meta": {
        "outputsToInstall": [
          "out"
        ],
        "description": "Reference library for reading, displaying, writing and examining Multiple-Image Network Graphics",
        "position": "/nix/store/lbf0kbc67zpm6xw6lia2fj1qskikaffz-source/pkgs/development/libraries/libmng/default.nix:18",
        "unfree": false
      }
    },
    "element": {
      "attrPath": [
        "legacyPackages",
        "aarch64-linux",
        "libmng"
      ],
      "originalUrl": "flake:nixpkgs",
      "outputs": null,
      "storePaths": [
        "/nix/store/scyqns8a6jij8bss704afsxr4vsgiyvx-libmng-2.0.3"
      ],
      "url": "github:flox/nixpkgs/d6490a0bd9dfb298fcd8382d3363b86870dc7340"
    },
    "source": {
      "locked": {
        "revCount": 410349,
        "lastModified": 1663761423
      }
    }
  }
}
