{
  "1.2.1": {
    "type": "catalogRender",
    "schema": 1,
    "eval": {
      "version": "1.2.1",
      "pname": "luppp",
      "name": "luppp-1.2.1",
      "system": "aarch64-linux",
      "outputs": {
        "out": "/nix/store/s8b5579h0vvb54470a8pixrmdjjgi4j3-luppp-1.2.1"
      },
      "meta": {
        "outputsToInstall": [
          "out"
        ],
        "description": "A music creation tool, intended for live use",
        "position": "/nix/store/lbf0kbc67zpm6xw6lia2fj1qskikaffz-source/pkgs/applications/audio/luppp/default.nix:42",
        "unfree": false
      }
    },
    "element": {
      "attrPath": [
        "legacyPackages",
        "aarch64-linux",
        "luppp"
      ],
      "originalUrl": "flake:nixpkgs",
      "outputs": null,
      "storePaths": [
        "/nix/store/s8b5579h0vvb54470a8pixrmdjjgi4j3-luppp-1.2.1"
      ],
      "url": "github:flox/nixpkgs/d6490a0bd9dfb298fcd8382d3363b86870dc7340"
    },
    "source": {
      "locked": {
        "revCount": 410349,
        "lastModified": 1663761423
      }
    }
  }
}
