{
  "0.3.4": {
    "type": "catalogRender",
    "schema": 1,
    "eval": {
      "version": "0.3.4",
      "pname": "timemachine",
      "name": "timemachine-0.3.4",
      "system": "aarch64-linux",
      "outputs": {
        "out": "/nix/store/pr0xyr9s8qcmqcvhkn5f3aybzd5v6npz-timemachine-0.3.4"
      },
      "meta": {
        "outputsToInstall": [
          "out"
        ],
        "description": "JACK audio recorder",
        "position": "/nix/store/a3i6cnnswvdg4k38jmibnjms65rjvyi7-source/pkgs/applications/audio/timemachine/default.nix:25",
        "unfree": false
      }
    },
    "element": {
      "attrPath": [
        "legacyPackages",
        "aarch64-linux",
        "timemachine"
      ],
      "originalUrl": "flake:nixpkgs",
      "outputs": null,
      "storePaths": [
        "/nix/store/pr0xyr9s8qcmqcvhkn5f3aybzd5v6npz-timemachine-0.3.4"
      ],
      "url": "github:flox/nixpkgs/dfd82985c273aac6eced03625f454b334daae2e8"
    },
    "source": {
      "locked": {
        "revCount": 379159,
        "lastModified": 1653060744
      }
    }
  }
}
