{
  "1.8.0": {
    "type": "catalogRender",
    "schema": 1,
    "eval": {
      "version": "1.8.0",
      "pname": "f2",
      "name": "f2-1.8.0",
      "system": "x86_64-darwin",
      "outputs": {
        "out": "/nix/store/53d3jcrfq4wryqgiq5yk6dlrkmz1bwq3-f2-1.8.0"
      },
      "meta": {
        "outputsToInstall": [
          "out"
        ],
        "description": "Command-line batch renaming tool",
        "position": "/nix/store/5g0bnn21bqpd241da9yyivjkcfy0ra1w-source/pkgs/tools/misc/f2/default.nix:22",
        "unfree": false
      }
    },
    "element": {
      "attrPath": "legacyPackages.x86_64-darwin.unstable.f2",
      "originalUrl": "flake:floxpkgs",
      "outputs": null,
      "storePaths": [
        "/nix/store/53d3jcrfq4wryqgiq5yk6dlrkmz1bwq3-f2-1.8.0"
      ],
      "url": "github:flox/floxpkgs/e0169d7a9d324afebf5679551407756c77af8930"
    },
    "source": {
      "locked": {
        "revCount": 384129,
        "lastModified": 1654682581
      }
    }
  }
}
