{
  "1.8.0": {
    "type": "catalogRender",
    "schema": 1,
    "eval": {
      "version": "1.8.0",
      "pname": "zita-resampler",
      "name": "zita-resampler-1.8.0",
      "system": "aarch64-linux",
      "outputs": {
        "out": "/nix/store/skg2rz4a9xwjxhn2ql9cxmgg54cyvb96-zita-resampler-1.8.0"
      },
      "meta": {
        "outputsToInstall": [
          "out"
        ],
        "description": "Resample library by Fons Adriaensen",
        "position": "/nix/store/5g0bnn21bqpd241da9yyivjkcfy0ra1w-source/pkgs/development/libraries/audio/zita-resampler/default.nix:31",
        "unfree": false
      }
    },
    "element": {
      "attrPath": "legacyPackages.aarch64-linux.unstable.zita-resampler",
      "originalUrl": "flake:floxpkgs",
      "outputs": null,
      "storePaths": [
        "/nix/store/skg2rz4a9xwjxhn2ql9cxmgg54cyvb96-zita-resampler-1.8.0"
      ],
      "url": "github:flox/floxpkgs/e0169d7a9d324afebf5679551407756c77af8930"
    },
    "source": {
      "locked": {
        "revCount": 384129,
        "lastModified": 1654682581
      }
    }
  }
}
