{
  "2.05.00": {
    "type": "catalogRender",
    "schema": 1,
    "eval": {
      "version": "2.05.00",
      "pname": "flexc++",
      "name": "flexc++-2.05.00",
      "system": "x86_64-linux",
      "outputs": {
        "out": "/nix/store/fagk922n56scyk4gvqm1h6pgs0nfqfbx-flexc++-2.05.00"
      },
      "meta": {
        "outputsToInstall": [
          "out"
        ],
        "description": "C++ tool for generating lexical scanners",
        "position": "/nix/store/9m8drnpifyl5qsx93g6ll2xw6wkps03z-source/pkgs/development/tools/parsing/flexc++/default.nix:37",
        "unfree": false
      }
    },
    "element": {
      "attrPath": [
        "legacyPackages",
        "x86_64-linux",
        "flexcpp"
      ],
      "originalUrl": "flake:nixpkgs",
      "outputs": null,
      "storePaths": [
        "/nix/store/fagk922n56scyk4gvqm1h6pgs0nfqfbx-flexc++-2.05.00"
      ],
      "url": "github:flox/nixpkgs/f994293d1eb8812f032e8919e10a594567cf6ef7"
    },
    "source": {
      "locked": {
        "revCount": 420742,
        "lastModified": 1666703756
      }
    }
  }
}
