{
  "5.1.3": {
    "type": "catalogRender",
    "schema": 1,
    "eval": {
      "version": "5.1.3",
      "pname": "gmp",
      "name": "gmp-5.1.3",
      "system": "x86_64-linux",
      "outputs": {
        "dev": "/nix/store/fsyzpsfkj1mnagpp7xhi18755a23j1df-gmp-5.1.3-dev",
        "info": "/nix/store/49y9f0ch4hz0k4vjdrg2fwzlhh3c5xdw-gmp-5.1.3-info",
        "out": "/nix/store/3n7fh8l5q4l7mzswpchr5l6i6jm114yx-gmp-5.1.3"
      },
      "meta": {
        "outputsToInstall": [
          "out"
        ],
        "description": "GNU multiple precision arithmetic library",
        "position": "/nix/store/9m8drnpifyl5qsx93g6ll2xw6wkps03z-source/pkgs/development/libraries/gmp/5.1.x.nix:56",
        "unfree": false
      }
    },
    "element": {
      "attrPath": [
        "legacyPackages",
        "x86_64-linux",
        "gmp5"
      ],
      "originalUrl": "flake:nixpkgs",
      "outputs": null,
      "storePaths": [
        "/nix/store/3n7fh8l5q4l7mzswpchr5l6i6jm114yx-gmp-5.1.3"
      ],
      "url": "github:flox/nixpkgs/f994293d1eb8812f032e8919e10a594567cf6ef7"
    },
    "source": {
      "locked": {
        "revCount": 420742,
        "lastModified": 1666703756
      }
    }
  }
}
