{
  "3.4.10": {
    "type": "catalogRender",
    "schema": 1,
    "eval": {
      "version": "3.4.10",
      "pname": "huggle",
      "name": "huggle-3.4.10",
      "system": "x86_64-linux",
      "outputs": {
        "out": "/nix/store/mqhkjgpdv7n93vjfhs3ifvbz5796ws8s-huggle-3.4.10"
      },
      "meta": {
        "outputsToInstall": [
          "out"
        ],
        "description": "Anti-vandalism tool for use on MediaWiki-based projects",
        "position": "/nix/store/9m8drnpifyl5qsx93g6ll2xw6wkps03z-source/pkgs/applications/misc/huggle/default.nix:57",
        "unfree": false
      }
    },
    "element": {
      "attrPath": [
        "legacyPackages",
        "x86_64-linux",
        "huggle"
      ],
      "originalUrl": "flake:nixpkgs",
      "outputs": null,
      "storePaths": [
        "/nix/store/mqhkjgpdv7n93vjfhs3ifvbz5796ws8s-huggle-3.4.10"
      ],
      "url": "github:flox/nixpkgs/f994293d1eb8812f032e8919e10a594567cf6ef7"
    },
    "source": {
      "locked": {
        "revCount": 420742,
        "lastModified": 1666703756
      }
    }
  }
}
