{
  "2022.06.16": {
    "type": "catalogRender",
    "schema": 1,
    "eval": {
      "version": "2022.06.16",
      "pname": "live555",
      "name": "live555-2022.06.16",
      "system": "x86_64-linux",
      "outputs": {
        "out": "/nix/store/il7jjw5452m0bil91hm3mjj6zpfd3xa2-live555-2022.06.16"
      },
      "meta": {
        "outputsToInstall": [
          "out"
        ],
        "description": "Set of C++ libraries for multimedia streaming, using open standard protocols (RTP/RTCP, RTSP, SIP)",
        "position": "/nix/store/9qqx4gk4qnqaqb102iwvhhwn2basmbdq-source/pkgs/development/libraries/live555/default.nix:69",
        "unfree": false
      }
    },
    "element": {
      "attrPath": [
        "legacyPackages",
        "x86_64-linux",
        "live555"
      ],
      "originalUrl": "flake:nixpkgs",
      "outputs": null,
      "storePaths": [
        "/nix/store/il7jjw5452m0bil91hm3mjj6zpfd3xa2-live555-2022.06.16"
      ],
      "url": "github:flox/nixpkgs/ce49cb7792a7ffd65ef352dda1110a4e4a204eac"
    },
    "source": {
      "locked": {
        "revCount": 394203,
        "lastModified": 1658826464
      }
    }
  },
  "2022.07.14": {
    "type": "catalogRender",
    "schema": 1,
    "eval": {
      "version": "2022.07.14",
      "pname": "live555",
      "name": "live555-2022.07.14",
      "system": "x86_64-linux",
      "outputs": {
        "out": "/nix/store/xi5jv6cnly3jz3ls4k68q93knp56h8r6-live555-2022.07.14"
      },
      "meta": {
        "outputsToInstall": [
          "out"
        ],
        "description": "Set of C++ libraries for multimedia streaming, using open standard protocols (RTP/RTCP, RTSP, SIP)",
        "position": "/nix/store/lbf0kbc67zpm6xw6lia2fj1qskikaffz-source/pkgs/development/libraries/live555/default.nix:69",
        "unfree": false
      }
    },
    "element": {
      "attrPath": [
        "legacyPackages",
        "x86_64-linux",
        "live555"
      ],
      "originalUrl": "flake:nixpkgs",
      "outputs": null,
      "storePaths": [
        "/nix/store/xi5jv6cnly3jz3ls4k68q93knp56h8r6-live555-2022.07.14"
      ],
      "url": "github:flox/nixpkgs/d6490a0bd9dfb298fcd8382d3363b86870dc7340"
    },
    "source": {
      "locked": {
        "revCount": 410349,
        "lastModified": 1663761423
      }
    }
  },
  "2022.02.07": {
    "type": "catalogRender",
    "schema": 1,
    "eval": {
      "version": "2022.02.07",
      "pname": "live555",
      "name": "live555-2022.02.07",
      "system": "x86_64-linux",
      "outputs": {
        "out": "/nix/store/w4vl25db0kln2gdk09svaxffncksch06-live555-2022.02.07"
      },
      "meta": {
        "outputsToInstall": [
          "out"
        ],
        "description": "Set of C++ libraries for multimedia streaming, using open standard protocols (RTP/RTCP, RTSP, SIP)",
        "position": "/nix/store/5g0bnn21bqpd241da9yyivjkcfy0ra1w-source/pkgs/development/libraries/live555/default.nix:75",
        "unfree": false
      }
    },
    "element": {
      "attrPath": [
        "legacyPackages",
        "x86_64-linux",
        "live555"
      ],
      "originalUrl": "flake:nixpkgs",
      "outputs": null,
      "storePaths": [
        "/nix/store/w4vl25db0kln2gdk09svaxffncksch06-live555-2022.02.07"
      ],
      "url": "github:flox/nixpkgs/e0169d7a9d324afebf5679551407756c77af8930"
    },
    "source": {
      "locked": {
        "revCount": 384129,
        "lastModified": 1654682581
      }
    }
  }
}
