{
  "1.3.1": {
    "type": "catalogRender",
    "schema": 1,
    "eval": {
      "version": "1.3.1",
      "pname": "f3d",
      "name": "f3d-1.3.1",
      "system": "x86_64-darwin",
      "outputs": {
        "out": "/nix/store/c533ww7fa0mqdvscqganrx6gckns1sgp-f3d-1.3.1"
      },
      "meta": {
        "outputsToInstall": [
          "out"
        ],
        "description": "Fast and minimalist 3D viewer using VTK",
        "position": "/nix/store/lbf0kbc67zpm6xw6lia2fj1qskikaffz-source/pkgs/applications/graphics/f3d/default.nix:29",
        "unfree": false
      }
    },
    "element": {
      "attrPath": [
        "legacyPackages",
        "x86_64-darwin",
        "f3d"
      ],
      "originalUrl": "flake:nixpkgs",
      "outputs": null,
      "storePaths": [
        "/nix/store/c533ww7fa0mqdvscqganrx6gckns1sgp-f3d-1.3.1"
      ],
      "url": "github:flox/nixpkgs/d6490a0bd9dfb298fcd8382d3363b86870dc7340"
    },
    "source": {
      "locked": {
        "revCount": 410349,
        "lastModified": 1663761423
      }
    }
  },
  "1.2.1": {
    "type": "catalogRender",
    "schema": 1,
    "eval": {
      "version": "1.2.1",
      "pname": "f3d",
      "name": "f3d-1.2.1",
      "system": "x86_64-darwin",
      "outputs": {
        "out": "/nix/store/0pnlhq10xqn3lbkh0lp7z6zvyzqamqff-f3d-1.2.1"
      },
      "meta": {
        "outputsToInstall": [
          "out"
        ],
        "description": "Fast and minimalist 3D viewer using VTK",
        "position": "/nix/store/bnyi6xm7xjdgvnhps0d01h5nqd4lgc0p-source/pkgs/applications/graphics/f3d/default.nix:21",
        "unfree": false
      }
    },
    "element": {
      "attrPath": [
        "legacyPackages",
        "x86_64-darwin",
        "f3d"
      ],
      "originalUrl": "flake:nixpkgs",
      "outputs": null,
      "storePaths": [
        "/nix/store/0pnlhq10xqn3lbkh0lp7z6zvyzqamqff-f3d-1.2.1"
      ],
      "url": "github:flox/nixpkgs/5e804cd8a27f835a402b22e086e36e797716ef8b"
    },
    "source": {
      "locked": {
        "revCount": 402830,
        "lastModified": 1661239211
      }
    }
  },
  "1.1.0": {
    "type": "catalogRender",
    "schema": 1,
    "eval": {
      "version": "1.1.0",
      "pname": "f3d",
      "name": "f3d-1.1.0",
      "system": "x86_64-darwin",
      "outputs": {
        "out": "/nix/store/z1484vrav413s966cp4k4bcqp5rmc894-f3d-1.1.0"
      },
      "meta": {
        "outputsToInstall": [
          "out"
        ],
        "description": "Fast and minimalist 3D viewer using VTK",
        "position": "/nix/store/9psm6wac3caf31niizrfgrvlnynckb5r-source/pkgs/applications/graphics/f3d/default.nix:22",
        "unfree": false
      }
    },
    "element": {
      "attrPath": [
        "legacyPackages",
        "x86_64-darwin",
        "f3d"
      ],
      "originalUrl": "flake:nixpkgs",
      "outputs": null,
      "storePaths": [
        "/nix/store/z1484vrav413s966cp4k4bcqp5rmc894-f3d-1.1.0"
      ],
      "url": "github:flox/nixpkgs/58a000460eefc7f7d903385d8f641485a08302f4"
    },
    "source": {
      "locked": {
        "revCount": 309392,
        "lastModified": 1629294066
      }
    }
  }
}
