{
  "2.7.1": {
    "type": "catalogRender",
    "schema": 1,
    "eval": {
      "version": "2.7.1",
      "pname": "gmic-qt",
      "name": "gmic-qt-2.7.1",
      "system": "x86_64-darwin",
      "outputs": {
        "out": "/nix/store/c8nwa8klp5akfgjr2gwmz8byk4imys9g-gmic-qt-2.7.1"
      },
      "meta": {
        "outputsToInstall": [
          "out"
        ],
        "description": "Versatile front-end to the image processing framework G'MIC",
        "position": "/nix/store/9psm6wac3caf31niizrfgrvlnynckb5r-source/pkgs/tools/graphics/gmic-qt/default.nix:139",
        "unfree": false
      }
    },
    "element": {
      "attrPath": [
        "legacyPackages",
        "x86_64-darwin",
        "gmic-qt"
      ],
      "originalUrl": "flake:nixpkgs",
      "outputs": null,
      "storePaths": [
        "/nix/store/c8nwa8klp5akfgjr2gwmz8byk4imys9g-gmic-qt-2.7.1"
      ],
      "url": "github:flox/nixpkgs/58a000460eefc7f7d903385d8f641485a08302f4"
    },
    "source": {
      "locked": {
        "revCount": 309392,
        "lastModified": 1629294066
      }
    }
  },
  "3.0.0": {
    "type": "catalogRender",
    "schema": 1,
    "eval": {
      "version": "3.0.0",
      "pname": "gmic-qt",
      "name": "gmic-qt-3.0.0",
      "system": "x86_64-darwin",
      "outputs": {
        "out": "/nix/store/bkr32x71302cbc3vnjfxl1yqx1b5q9i7-gmic-qt-3.0.0"
      },
      "meta": {
        "outputsToInstall": [
          "out"
        ],
        "description": "Versatile front-end to the image processing framework G'MIC",
        "position": "/nix/store/a3i6cnnswvdg4k38jmibnjms65rjvyi7-source/pkgs/tools/graphics/gmic-qt/default.nix:163",
        "unfree": false
      }
    },
    "element": {
      "attrPath": [
        "legacyPackages",
        "x86_64-darwin",
        "gmic-qt"
      ],
      "originalUrl": "flake:nixpkgs",
      "outputs": null,
      "storePaths": [
        "/nix/store/bkr32x71302cbc3vnjfxl1yqx1b5q9i7-gmic-qt-3.0.0"
      ],
      "url": "github:flox/nixpkgs/dfd82985c273aac6eced03625f454b334daae2e8"
    },
    "source": {
      "locked": {
        "revCount": 379159,
        "lastModified": 1653060744
      }
    }
  }
}
