{
  "3.24.5": {
    "type": "catalogRender",
    "schema": 1,
    "eval": {
      "version": "3.24.5",
      "pname": "gtkmm",
      "name": "gtkmm-3.24.5",
      "system": "x86_64-darwin",
      "outputs": {
        "dev": "/nix/store/ry04a05sja9ggiwrybk69rm85wbpy8g5-gtkmm-3.24.5-dev",
        "out": "/nix/store/yzwsf9afpa0dpsdyc64lh7jd9aki4djl-gtkmm-3.24.5"
      },
      "meta": {
        "outputsToInstall": [
          "out"
        ],
        "description": "C++ interface to the GTK graphical user interface library",
        "position": "/nix/store/x0dxzk94zhkkxjavadj2bpjimgxajivx-source/pkgs/development/libraries/gtkmm/3.x.nix:32",
        "unfree": false
      }
    },
    "element": {
      "attrPath": [
        "legacyPackages",
        "x86_64-darwin",
        "gtkmm3"
      ],
      "originalUrl": "flake:nixpkgs",
      "outputs": null,
      "storePaths": [
        "/nix/store/yzwsf9afpa0dpsdyc64lh7jd9aki4djl-gtkmm-3.24.5"
      ],
      "url": "github:flox/nixpkgs/90705c89fbad69c4c971fabf2b1edd8c7875b5d6"
    },
    "source": {
      "locked": {
        "revCount": 360804,
        "lastModified": 1652991527
      }
    }
  },
  "3.24.6": {
    "type": "catalogRender",
    "schema": 1,
    "eval": {
      "version": "3.24.6",
      "pname": "gtkmm",
      "name": "gtkmm-3.24.6",
      "system": "x86_64-darwin",
      "outputs": {
        "dev": "/nix/store/l8knb43mh5qgrfbdn93y2qkqndna4v8w-gtkmm-3.24.6-dev",
        "out": "/nix/store/dglims9bnpsrjb89djmv8hg5cynzrryw-gtkmm-3.24.6"
      },
      "meta": {
        "outputsToInstall": [
          "out"
        ],
        "description": "C++ interface to the GTK graphical user interface library",
        "position": "/nix/store/a3i6cnnswvdg4k38jmibnjms65rjvyi7-source/pkgs/development/libraries/gtkmm/3.x.nix:32",
        "unfree": false
      }
    },
    "element": {
      "attrPath": [
        "legacyPackages",
        "x86_64-darwin",
        "gtkmm3"
      ],
      "originalUrl": "flake:nixpkgs",
      "outputs": null,
      "storePaths": [
        "/nix/store/dglims9bnpsrjb89djmv8hg5cynzrryw-gtkmm-3.24.6"
      ],
      "url": "github:flox/nixpkgs/dfd82985c273aac6eced03625f454b334daae2e8"
    },
    "source": {
      "locked": {
        "revCount": 379159,
        "lastModified": 1653060744
      }
    }
  }
}
