{
  "unknown": {
    "type": "catalogRender",
    "schema": 1,
    "eval": {
      "version": "unknown",
      "pname": null,
      "name": "openvpn-learnaddress-19b03c3",
      "system": "x86_64-darwin",
      "outputs": {
        "out": "/nix/store/nizmrwp23wcvcjva916lcqwnf3nk0fmf-openvpn-learnaddress-19b03c3"
      },
      "meta": {
        "outputsToInstall": [
          "out"
        ],
        "description": "Openvpn learn-address script to manage a hosts-like file",
        "position": "/nix/store/9psm6wac3caf31niizrfgrvlnynckb5r-source/pkgs/tools/networking/openvpn/openvpn_learnaddress.nix:23",
        "unfree": false
      }
    },
    "element": {
      "attrPath": "legacyPackages.x86_64-darwin.stable.openvpn_learnaddress",
      "originalUrl": "flake:floxpkgs",
      "outputs": null,
      "storePaths": [
        "/nix/store/nizmrwp23wcvcjva916lcqwnf3nk0fmf-openvpn-learnaddress-19b03c3"
      ],
      "url": "github:flox/floxpkgs/58a000460eefc7f7d903385d8f641485a08302f4"
    },
    "source": {
      "locked": {
        "revCount": 309392,
        "lastModified": 1629294066
      }
    }
  },
  "unstable-2013-10-21": {
    "type": "catalogRender",
    "schema": 1,
    "eval": {
      "version": "unstable-2013-10-21",
      "pname": "openvpn-learnaddress",
      "name": "openvpn-learnaddress-unstable-2013-10-21",
      "system": "x86_64-darwin",
      "outputs": {
        "out": "/nix/store/1lbf0a6y2qa1hm88h7h08gxcqy7jmsmp-openvpn-learnaddress-unstable-2013-10-21"
      },
      "meta": {
        "outputsToInstall": [
          "out"
        ],
        "description": "Openvpn learn-address script to manage a hosts-like file",
        "position": "/nix/store/a3i6cnnswvdg4k38jmibnjms65rjvyi7-source/pkgs/tools/networking/openvpn/openvpn_learnaddress.nix:24",
        "unfree": false
      }
    },
    "element": {
      "attrPath": "legacyPackages.x86_64-darwin.stable.openvpn_learnaddress",
      "originalUrl": "flake:floxpkgs",
      "outputs": null,
      "storePaths": [
        "/nix/store/1lbf0a6y2qa1hm88h7h08gxcqy7jmsmp-openvpn-learnaddress-unstable-2013-10-21"
      ],
      "url": "github:flox/floxpkgs/dfd82985c273aac6eced03625f454b334daae2e8"
    },
    "source": {
      "locked": {
        "revCount": 379159,
        "lastModified": 1653060744
      }
    }
  }
}
