{
  "0.8.9.0": {
    "type": "catalogRender",
    "schema": 1,
    "eval": {
      "version": "0.8.9.0",
      "pname": "libmodplug",
      "name": "libmodplug-0.8.9.0",
      "system": "aarch64-darwin",
      "outputs": {
        "out": "/nix/store/1b09542ay8kn665iyy3c327r9191m3xa-libmodplug-0.8.9.0"
      },
      "meta": {
        "outputsToInstall": [
          "out"
        ],
        "description": "MOD playing library",
        "position": "/nix/store/5g0bnn21bqpd241da9yyivjkcfy0ra1w-source/pkgs/development/libraries/libmodplug/default.nix:14",
        "unfree": false
      }
    },
    "element": {
      "attrPath": "legacyPackages.aarch64-darwin.unstable.libmodplug",
      "originalUrl": "flake:floxpkgs",
      "outputs": null,
      "storePaths": [
        "/nix/store/1b09542ay8kn665iyy3c327r9191m3xa-libmodplug-0.8.9.0"
      ],
      "url": "github:flox/floxpkgs/e0169d7a9d324afebf5679551407756c77af8930"
    },
    "source": {
      "locked": {
        "revCount": 384129,
        "lastModified": 1654682581
      }
    }
  }
}
